{
    "camera_coord_3d": true,
    "ckpt": "checkpoint/default_lsp",
    "ckpt_ims": "checkpoint/default_lsp/ims",
    "data_dir": "/home/mronchi/Storage/Datasets/lsp/lsp_dataset/",
    "dataset_type": "lsp_14k",
    "distance_multiplier": 2.5,
    "dropout": 0.5,
    "epochs": 110,
    "exp": "default_lsp",
    "is_test": true,
    "is_train": true,
    "job": 8,
    "keep_root": true,
    "limb_type": "avg_person",
    "linear_size": 1024,
    "load": "",
    "loss_weights": {
        "jsd": 1.0,
        "relative": 1.0,
        "reproj": 1.0,
        "root": 1.0,
        "symm": 1.0
    },
    "lr": 0.001,
    "lr_decay": 100000,
    "lr_gamma": 0.96,
    "max_norm": true,
    "mturk_data": "./mturk_data/relative_depth_lsp_v1.json",
    "num_pairs": 1,
    "num_stage": 1,
    "only_depth": false,
    "predict_scale": true,
    "reprojection": "scaled_orthographic",
    "resume": false,
    "save_ims": true,
    "scale_range": 3,
    "standardize_input_data": true,
    "standardize_output_data": false,
    "subtract_2d_root": true,
    "test_batch": 64,
    "test_step": 1,
    "tolerance_mm": 0.0,
    "train_batch": 256,
    "unnorm_init": 100.0,
    "unnorm_op": true,
    "use_full_intrinsics": false,
    "use_loaded_stats": false,
    "use_rel_loss": true
}